nanomethphase/DSS_DMA.R
nanomethphase/__init__.py
nanomethphase/__main__.py
nanomethphase-1.0.dist-info/LICENSE
nanomethphase-1.0.dist-info/METADATA
nanomethphase-1.0.dist-info/WHEEL
nanomethphase-1.0.dist-info/entry_points.txt
nanomethphase-1.0.dist-info/top_level.txt
nanomethphase-1.0.dist-info/RECORD
