Metadata-Version: 2.1
Name: nanomethphase
Version: 1.0
Summary: Phase long reads from Oxford Nanopore Technologies based on their methylated profile.
Home-page: UNKNOWN
Author: Vahid Akbari
Author-email: vakbari@bcgsc.ca
License: UNKNOWN
Project-URL: GitHub, https://github.com/vahidAK/NanoMethPhase
Platform: UNKNOWN
Classifier: Programming Language :: Python :: 3
Classifier: License :: OSI Approved :: GNU General Public License v3 (GPLv3)
Classifier: Operating System :: Unix
Classifier: Operating System :: POSIX :: Linux
Requires-Python: >=3.7
Requires-Dist: numpy (<1.19.0,>=1.16.0)
Requires-Dist: pysam (>=0.15.4)
Requires-Dist: pytabix (>=0.0.2)
Requires-Dist: tqdm (>=4.36.1)
Requires-Dist: snvoter (>=1.0)
